CHANGES.txt
LICENSE.txt
MANIFEST.in
README.md
README_pypi.txt
requirements_dev.txt
setup.py
apitree/__init__.py
apitree/api_doc_template.mako
apitree/api_documentation.py
apitree/exc.py
apitree/tree_scan.py
apitree/util.py
apitree/view_callable.py
apitree.egg-info/PKG-INFO
apitree.egg-info/SOURCES.txt
apitree.egg-info/dependency_links.txt
apitree.egg-info/requires.txt
apitree.egg-info/top_level.txt