Metadata-Version: 1.0
Name: apitree
Version: 0.3.3
Summary: Build an orderly web service API backend.
Home-page: https://github.com/jmatthias/apitree
Author: Josh Matthias
Author-email: python.apitree@gmail.com
License: LICENSE.txt
Platform: UNKNOWN
